tdc7201/__init__.py
tdc7201-0.11.2.dist-info/METADATA
tdc7201-0.11.2.dist-info/WHEEL
tdc7201-0.11.2.dist-info/top_level.txt
tdc7201-0.11.2.dist-info/RECORD
