Metadata-Version: 2.1
Name: tdc7201
Version: 0.11.2
Summary: Raspberry Pi driver for Texas Instruments TDC7201 Time-to-Digital-Converter chip
Home-page: https://github.com/HowardALandman/QTD/tree/master/src/tdc7201
Author: Howard A. Landman
Author-email: howard@riverrock.org
License: GPLv3+
Platform: UNKNOWN
Classifier: Development Status :: 4 - Beta
Classifier: Intended Audience :: Developers
Classifier: Intended Audience :: Science/Research
Classifier: License :: OSI Approved :: GNU General Public License v3 or later (GPLv3+)
Classifier: Natural Language :: English
Classifier: Operating System :: POSIX :: Linux
Classifier: Programming Language :: Python :: 3
Classifier: Programming Language :: Python :: 3 :: Only
Classifier: Programming Language :: Python :: 3.6
Classifier: Programming Language :: Python :: 3.7
Classifier: Topic :: Scientific/Engineering
Classifier: Topic :: Scientific/Engineering :: Physics
Classifier: Topic :: Software Development :: Libraries :: Python Modules
Classifier: Topic :: System :: Hardware
Classifier: Topic :: System :: Hardware :: Hardware Drivers
Requires-Dist: RPi.GPIO (>=0.5)
Requires-Dist: spidev (>=3.5)
